parse_web/__init__.py
parse_web/pars.py
parse_web-1.0.0.dist-info/LICENCE
parse_web-1.0.0.dist-info/METADATA
parse_web-1.0.0.dist-info/WHEEL
parse_web-1.0.0.dist-info/top_level.txt
parse_web-1.0.0.dist-info/RECORD
