Metadata-Version: 2.1
Name: parse_web
Version: 1.0.0
Summary: Access to website information 👽 
Author-email: Majid Barmaki  <magidbarmaky@gmail.com>
Project-URL: Homepage, https://github.com/magidbarmaky/parse_web
Project-URL: telegram, https://t.me/the_developerman
Classifier: Programming Language :: Python :: 3
Classifier: License :: OSI Approved :: MIT License
Classifier: Operating System :: OS Independent
Requires-Python: >=3.7
License-File: LICENCE
